{"commitInfo":{"timestamp":1775492273467,"operation":"WRITE","operationParameters":{"mode":"Append"},"engineInfo":"delta-rs:py-1.5.0","clientVersion":"delta-rs.py-1.5.0","operationMetrics":{"execution_time_ms":3,"num_added_files":1,"num_added_rows":1,"num_partitions":0,"num_removed_files":0}}}
{"add":{"path":"part-00000-136682f7-6d98-4da8-b355-0d01b5c59e2a-c000.snappy.parquet","partitionValues":{},"size":2221,"modificationTime":1775492273467,"dataChange":true,"stats":"{\"numRecords\":1,\"minValues\":{\"valor_passagem_base\":140.78,\"tempo_estimado_minutos\":105,\"id\":263,\"distancia_km\":625.52,\"cidade_destino\":\"Pereira de Goiás\",\"cidade_origem\":\"Ferreira do Galho\"},\"maxValues\":{\"cidade_origem\":\"Ferreira do Galho\",\"distancia_km\":625.52,\"valor_passagem_base\":140.78,\"id\":263,\"cidade_destino\":\"Pereira de Goiás\",\"tempo_estimado_minutos\":105},\"nullCount\":{\"distancia_km\":0,\"cidade_origem\":0,\"cidade_destino\":0,\"tempo_estimado_minutos\":0,\"id\":0,\"valor_passagem_base\":0}}","tags":null,"baseRowId":null,"defaultRowCommitVersion":null,"clusteringProvider":null}}