{"commitInfo":{"timestamp":1775492274248,"operation":"WRITE","operationParameters":{"mode":"Append"},"engineInfo":"delta-rs:py-1.5.0","clientVersion":"delta-rs.py-1.5.0","operationMetrics":{"execution_time_ms":2,"num_added_files":1,"num_added_rows":1,"num_partitions":0,"num_removed_files":0}}}
{"add":{"path":"part-00000-fd357ab3-ebb8-4393-beca-f945d995a8da-c000.snappy.parquet","partitionValues":{},"size":2241,"modificationTime":1775492274248,"dataChange":true,"stats":"{\"numRecords\":1,\"minValues\":{\"valor_passagem_base\":154.76,\"distancia_km\":139.84,\"id\":273,\"cidade_destino\":\"Camargo da Praia\",\"tempo_estimado_minutos\":384,\"cidade_origem\":\"da Mota de Casa Grande\"},\"maxValues\":{\"id\":273,\"cidade_destino\":\"Camargo da Praia\",\"distancia_km\":139.84,\"valor_passagem_base\":154.76,\"cidade_origem\":\"da Mota de Casa Grande\",\"tempo_estimado_minutos\":384},\"nullCount\":{\"tempo_estimado_minutos\":0,\"cidade_destino\":0,\"id\":0,\"cidade_origem\":0,\"distancia_km\":0,\"valor_passagem_base\":0}}","tags":null,"baseRowId":null,"defaultRowCommitVersion":null,"clusteringProvider":null}}