{"commitInfo":{"timestamp":1775489855309,"operation":"UPDATE","operationParameters":{"predicate":"id = 301"},"engineInfo":"delta-rs:py-1.5.0","readVersion":300,"operationMetrics":{"execution_time_ms":61,"num_added_files":1,"num_copied_rows":0,"num_removed_files":1,"num_updated_rows":1,"scan_time_ms":41},"clientVersion":"delta-rs.py-1.5.0"}}
{"add":{"path":"part-00000-e60a49a7-1bf3-4698-b098-34a827516abc-c000.snappy.parquet","partitionValues":{},"size":1933,"modificationTime":1775489855305,"dataChange":true,"stats":"{\"numRecords\":1,\"minValues\":{\"modelo\":\"Mercedes-Benz\",\"ano_fabricacao\":2002,\"id\":301,\"placa\":\"ACB-1234\",\"em_manutencao\":false,\"capacidade\":40},\"maxValues\":{\"em_manutencao\":false,\"id\":301,\"capacidade\":40,\"ano_fabricacao\":2002,\"placa\":\"ACB-1234\",\"modelo\":\"Mercedes-Benz\"},\"nullCount\":{\"placa\":0,\"id\":0,\"modelo\":0,\"em_manutencao\":0,\"capacidade\":0,\"ano_fabricacao\":0}}","tags":null,"baseRowId":null,"defaultRowCommitVersion":null,"clusteringProvider":null}}
{"remove":{"path":"part-00000-1a708531-baec-4253-a107-d0be6867d49f-c000.snappy.parquet","dataChange":true,"deletionTimestamp":1775489855306,"extendedFileMetadata":true,"partitionValues":{},"size":1933}}