{"commitInfo":{"timestamp":1775489254165,"operation":"WRITE","operationParameters":{"mode":"Append"},"engineInfo":"delta-rs:py-1.5.0","clientVersion":"delta-rs.py-1.5.0","operationMetrics":{"execution_time_ms":1,"num_added_files":1,"num_added_rows":1,"num_partitions":0,"num_removed_files":0}}}
{"add":{"path":"part-00000-fc8d9dc7-fec1-48d2-964f-16bb2f63cbdf-c000.snappy.parquet","partitionValues":{},"size":1918,"modificationTime":1775489254165,"dataChange":true,"stats":"{\"numRecords\":1,\"minValues\":{\"em_manutencao\":false,\"id\":123,\"capacidade\":50,\"modelo\":\"Scania K310\",\"ano_fabricacao\":2012,\"placa\":\"NSL4P33\"},\"maxValues\":{\"capacidade\":50,\"modelo\":\"Scania K310\",\"id\":123,\"ano_fabricacao\":2012,\"em_manutencao\":false,\"placa\":\"NSL4P33\"},\"nullCount\":{\"modelo\":0,\"placa\":0,\"id\":0,\"capacidade\":0,\"em_manutencao\":0,\"ano_fabricacao\":0}}","tags":null,"baseRowId":null,"defaultRowCommitVersion":null,"clusteringProvider":null}}