{"commitInfo":{"timestamp":1775489258579,"operation":"WRITE","operationParameters":{"mode":"Append"},"engineInfo":"delta-rs:py-1.5.0","clientVersion":"delta-rs.py-1.5.0","operationMetrics":{"execution_time_ms":1,"num_added_files":1,"num_added_rows":1,"num_partitions":0,"num_removed_files":0}}}
{"add":{"path":"part-00000-6f083eb1-9f3c-4e9f-ad92-07e1207de885-c000.snappy.parquet","partitionValues":{},"size":1954,"modificationTime":1775489258579,"dataChange":true,"stats":"{\"numRecords\":1,\"minValues\":{\"modelo\":\"Mercedes-Benz O500\",\"em_manutencao\":false,\"id\":234,\"placa\":\"TVA9L85\",\"capacidade\":50,\"ano_fabricacao\":2020},\"maxValues\":{\"em_manutencao\":false,\"placa\":\"TVA9L85\",\"id\":234,\"modelo\":\"Mercedes-Benz O500\",\"capacidade\":50,\"ano_fabricacao\":2020},\"nullCount\":{\"placa\":0,\"modelo\":0,\"capacidade\":0,\"em_manutencao\":0,\"ano_fabricacao\":0,\"id\":0}}","tags":null,"baseRowId":null,"defaultRowCommitVersion":null,"clusteringProvider":null}}