{"commitInfo":{"timestamp":1775492262869,"operation":"WRITE","operationParameters":{"mode":"Append"},"engineInfo":"delta-rs:py-1.5.0","clientVersion":"delta-rs.py-1.5.0","operationMetrics":{"execution_time_ms":1,"num_added_files":1,"num_added_rows":1,"num_partitions":0,"num_removed_files":0}}}
{"add":{"path":"part-00000-feece4b6-a587-4e1e-b9b0-b56e7cb656ab-c000.snappy.parquet","partitionValues":{},"size":1954,"modificationTime":1775492262869,"dataChange":true,"stats":"{\"numRecords\":1,\"minValues\":{\"modelo\":\"Mercedes-Benz O500\",\"id\":469,\"em_manutencao\":true,\"capacidade\":50,\"ano_fabricacao\":2013,\"placa\":\"NJM1U51\"},\"maxValues\":{\"em_manutencao\":true,\"ano_fabricacao\":2013,\"modelo\":\"Mercedes-Benz O500\",\"id\":469,\"capacidade\":50,\"placa\":\"NJM1U51\"},\"nullCount\":{\"ano_fabricacao\":0,\"id\":0,\"modelo\":0,\"placa\":0,\"em_manutencao\":0,\"capacidade\":0}}","tags":null,"baseRowId":null,"defaultRowCommitVersion":null,"clusteringProvider":null}}