{"commitInfo":{"timestamp":1775489251303,"operation":"WRITE","operationParameters":{"mode":"Append"},"engineInfo":"delta-rs:py-1.5.0","operationMetrics":{"execution_time_ms":1,"num_added_files":1,"num_added_rows":1,"num_partitions":0,"num_removed_files":0},"clientVersion":"delta-rs.py-1.5.0"}}
{"add":{"path":"part-00000-ec6621ae-8bd9-4d2d-bc82-7ee61ebea6e8-c000.snappy.parquet","partitionValues":{},"size":1918,"modificationTime":1775489251303,"dataChange":true,"stats":"{\"numRecords\":1,\"minValues\":{\"modelo\":\"Scania K310\",\"capacidade\":42,\"em_manutencao\":false,\"id\":37,\"placa\":\"QZZ9W39\",\"ano_fabricacao\":2022},\"maxValues\":{\"placa\":\"QZZ9W39\",\"modelo\":\"Scania K310\",\"ano_fabricacao\":2022,\"capacidade\":42,\"id\":37,\"em_manutencao\":false},\"nullCount\":{\"placa\":0,\"modelo\":0,\"capacidade\":0,\"ano_fabricacao\":0,\"em_manutencao\":0,\"id\":0}}","tags":null,"baseRowId":null,"defaultRowCommitVersion":null,"clusteringProvider":null}}