{"commitInfo":{"timestamp":1775489273168,"operation":"WRITE","operationParameters":{"mode":"Append"},"engineInfo":"delta-rs:py-1.5.0","operationMetrics":{"execution_time_ms":1,"num_added_files":1,"num_added_rows":1,"num_partitions":0,"num_removed_files":0},"clientVersion":"delta-rs.py-1.5.0"}}
{"add":{"path":"part-00000-56c9a4e8-aeef-4c04-b2c5-1607f6932264-c000.snappy.parquet","partitionValues":{},"size":2129,"modificationTime":1775489273168,"dataChange":true,"stats":"{\"numRecords\":1,\"minValues\":{\"status\":\"Em Curso\",\"motorista_nome\":\"Clara Fernandes\",\"id_onibus\":6,\"id\":145,\"data_hora_partida\":\"2026-05-12T12:27:53.150200\",\"id_rota\":145},\"maxValues\":{\"data_hora_partida\":\"2026-05-12T12:27:53.150200\",\"motorista_nome\":\"Clara Fernandes\",\"id_onibus\":6,\"status\":\"Em Curso\",\"id_rota\":145,\"id\":145},\"nullCount\":{\"motorista_nome\":0,\"id_onibus\":0,\"data_hora_partida\":0,\"id_rota\":0,\"status\":0,\"id\":0}}","tags":null,"baseRowId":null,"defaultRowCommitVersion":null,"clusteringProvider":null}}