{"commitInfo":{"timestamp":1775492314588,"operation":"WRITE","operationParameters":{"mode":"Append"},"engineInfo":"delta-rs:py-1.5.0","clientVersion":"delta-rs.py-1.5.0","operationMetrics":{"execution_time_ms":2,"num_added_files":1,"num_added_rows":1,"num_partitions":0,"num_removed_files":0}}}
{"add":{"path":"part-00000-d4958ddd-b10e-476c-8eb2-9bf26fe881f8-c000.snappy.parquet","partitionValues":{},"size":2104,"modificationTime":1775492314588,"dataChange":true,"stats":"{\"numRecords\":1,\"minValues\":{\"data_hora_partida\":\"2026-05-08T13:18:34.559610\",\"motorista_nome\":\"Ian Santos\",\"id_onibus\":51,\"id_rota\":10,\"id\":1054,\"status\":\"Em Curso\"},\"maxValues\":{\"status\":\"Em Curso\",\"id\":1054,\"motorista_nome\":\"Ian Santos\",\"id_rota\":10,\"id_onibus\":51,\"data_hora_partida\":\"2026-05-08T13:18:34.559610\"},\"nullCount\":{\"data_hora_partida\":0,\"motorista_nome\":0,\"status\":0,\"id_onibus\":0,\"id_rota\":0,\"id\":0}}","tags":null,"baseRowId":null,"defaultRowCommitVersion":null,"clusteringProvider":null}}